setup.py
dreemchest/__init__.py
dreemchest/__main__.py
dreemchest/checkout.py
dreemchest/cmake.py
dreemchest/command_line.py
dreemchest/configure.py
dreemchest/git.py
dreemchest/install.py
dreemchest/main.py
dreemchest.egg-info/PKG-INFO
dreemchest.egg-info/SOURCES.txt
dreemchest.egg-info/dependency_links.txt
dreemchest.egg-info/not-zip-safe
dreemchest.egg-info/top_level.txt