Metadata-Version: 1.0
Name: dreemchest
Version: 0.25
Summary: Dreemchest engine command line tool.
Home-page: https://github.com/dmsovetov/Dreemchest
Author: Dmitry Sovetov
Author-email: dmsovetov@gmail.com
License: MIT
Platform: UNKNOWN
